cmit/__init__.py
cmit/abc.py
cmit/client.py
cmit/messages.py
cmit/server.py
cmit/typing.py
cmit/utils.py
cmit/requests/__init__.py
cmit/requests/_internal_utils.py
cmit/requests/adapters.py
cmit/requests/api.py
cmit/requests/exceptions.py
cmit/requests/models.py
cmit/requests/sessions.py
cmit-0.1.0.dist-info/AUTHORS
cmit-0.1.0.dist-info/LICENSE
cmit-0.1.0.dist-info/METADATA
cmit-0.1.0.dist-info/WHEEL
cmit-0.1.0.dist-info/top_level.txt
cmit-0.1.0.dist-info/RECORD
