Metadata-Version: 2.1
Name: cmit
Version: 0.1.0
Summary: A text-based protocol to support internal process communication (IPC) within a single node.
Author: Bigelow Systems, LLC.
Author-email: Jordan Bigelow <jordan@jordanbigelow.com>, Bigelow Systems <engineering+cmit@bigelow.systems>
License: Copyright (c) 2023 Bigelow Systems, LLC and individual contributors.
Project-URL: Homepage, https://github.com/bigelow-systems/cmit
Project-URL: Issues, https://github.com/bigelow-systems/cmit/issues
Keywords: ipc,process,communication,text,protocol,cmit
Classifier: Development Status :: 3 - Alpha
Classifier: Intended Audience :: Developers
Classifier: License :: OSI Approved :: MIT License
Classifier: Programming Language :: Python :: 3.6
Classifier: Programming Language :: Python :: 3.7
Classifier: Topic :: Communications
Classifier: Topic :: Software Development :: Libraries :: Python Modules
Classifier: Topic :: System :: Distributed Computing
Classifier: Topic :: System :: Networking
Classifier: Topic :: System :: Systems Administration
Classifier: Topic :: Utilities
Requires-Python: >=3.6
License-File: LICENSE
License-File: AUTHORS
